{
  "Ivy": "https://inaturalist-open-data.s3.amazonaws.com/photos/8874/medium.jpg",
  "Fern": "https://inaturalist-open-data.s3.amazonaws.com/photos/383134769/medium.jpg",
  "Horse Chestnut": "https://inaturalist-open-data.s3.amazonaws.com/photos/277035469/medium.jpg",
  "Hosta": "https://inaturalist-open-data.s3.amazonaws.com/photos/5044116/medium.jpg",
  "Primrose": "https://inaturalist-open-data.s3.amazonaws.com/photos/121441132/medium.jpeg",
  "Hellebore": "https://inaturalist-open-data.s3.amazonaws.com/photos/129437915/medium.jpg",
  "Aquilegia": "https://inaturalist-open-data.s3.amazonaws.com/photos/245963537/medium.jpg",
  "Hart's Tongue Fern": "https://static.inaturalist.org/photos/42121986/medium.jpg",
  "Silver Birch": "https://inaturalist-open-data.s3.amazonaws.com/photos/36257611/medium.jpeg",
  "Navelwort": "https://inaturalist-open-data.s3.amazonaws.com/photos/1165740/medium.jpg",
  "Privet": "https://inaturalist-open-data.s3.amazonaws.com/photos/126520804/medium.jpeg",
  "Bluebell": "https://inaturalist-open-data.s3.amazonaws.com/photos/93374/medium.jpg",
  "Daffodil": "https://static.inaturalist.org/photos/119190821/medium.jpg",
  "Snowdrop": "https://inaturalist-open-data.s3.amazonaws.com/photos/112148867/medium.jpg",
  "Sycamore": "https://static.inaturalist.org/photos/53697442/medium.jpeg",
  "Raspberry": "https://inaturalist-open-data.s3.amazonaws.com/photos/358785151/medium.jpg",
  "Hornbeam": "https://static.inaturalist.org/photos/566113101/medium.jpg",
  "Perennial Ryegrass": "https://inaturalist-open-data.s3.amazonaws.com/photos/238799434/medium.jpg"
,
  "Hollyhock": "https://static.inaturalist.org/photos/153872572/medium.jpg",
  "Garden Rocket": "https://inaturalist-open-data.s3.amazonaws.com/photos/280772297/medium.jpeg",
  "Apple": "https://inaturalist-open-data.s3.amazonaws.com/photos/2066379/medium.JPG",
  "Hawthorn": "https://inaturalist-open-data.s3.amazonaws.com/photos/76382616/medium.jpg",
  "Foxglove": "https://static.inaturalist.org/photos/409784/medium.jpg",
  "Grape": "https://inaturalist-open-data.s3.amazonaws.com/photos/2809716/medium.jpg",
  "Cherry Laurel": "https://inaturalist-open-data.s3.amazonaws.com/photos/146285013/medium.jpg",
  "Buddleja": "https://static.inaturalist.org/photos/55578/medium.jpg",
  "Tomato": "https://inaturalist-open-data.s3.amazonaws.com/photos/232226140/medium.jpg",
  "Yellow Rose": "https://inaturalist-open-data.s3.amazonaws.com/photos/122545712/medium.jpeg",
  "Pink Rose": "https://inaturalist-open-data.s3.amazonaws.com/photos/220166524/medium.jpeg",
  "Red Rose": "https://inaturalist-open-data.s3.amazonaws.com/photos/633279/medium.jpg",
  "Cherry Blossom": "https://inaturalist-open-data.s3.amazonaws.com/photos/94761507/medium.jpeg",
  "Hydrangea": "https://inaturalist-open-data.s3.amazonaws.com/photos/79182087/medium.jpg",
  "Strawberry": "https://inaturalist-open-data.s3.amazonaws.com/photos/91052/medium.jpg",
  "Lavender": "https://inaturalist-open-data.s3.amazonaws.com/photos/116644427/medium.jpeg",
  "Crocosmia": "https://inaturalist-open-data.s3.amazonaws.com/photos/43084170/medium.jpg",
  "Geranium": "https://inaturalist-open-data.s3.amazonaws.com/photos/70283238/medium.jpg",
  "Acer": "https://inaturalist-open-data.s3.amazonaws.com/photos/27342760/medium.jpeg",
  "Willow Tree": "https://inaturalist-open-data.s3.amazonaws.com/photos/59393301/medium.jpeg",
  "Rhododendron": "https://static.inaturalist.org/photos/132769155/medium.jpg",
  "Euonymus": "https://static.inaturalist.org/photos/6358583/medium.jpg",
  "Phormium": "https://inaturalist-open-data.s3.amazonaws.com/photos/450688894/medium.jpeg",
  "Fuchsia": "https://inaturalist-open-data.s3.amazonaws.com/photos/45778546/medium.jpg",
  "Osmanthus": "https://inaturalist-open-data.s3.amazonaws.com/photos/1472053/medium.jpg",
  "Sedum": "https://inaturalist-open-data.s3.amazonaws.com/photos/137304118/medium.jpeg",
  "Photinia": "https://inaturalist-open-data.s3.amazonaws.com/photos/342304993/medium.jpg",
  "Camellia": "https://inaturalist-open-data.s3.amazonaws.com/photos/259793413/medium.jpg",
  "Red Maple": "https://inaturalist-open-data.s3.amazonaws.com/photos/371065093/medium.jpg",
  "Chive": "https://inaturalist-open-data.s3.amazonaws.com/photos/90411579/medium.jpg",
  "Oregano": "https://inaturalist-open-data.s3.amazonaws.com/photos/48569403/medium.jpg",
  "Shrubby Cinquefoil": "https://static.inaturalist.org/photos/21599193/medium.jpeg",
  "Hosta Undulata": "https://inaturalist-open-data.s3.amazonaws.com/photos/47727801/medium.jpg",
  "Gladioli": "https://static.inaturalist.org/photos/67419595/medium.jpg",
  "Shasta Daisy": "https://static.inaturalist.org/photos/3893205/medium.jpg",
  "Hemerocallis": "https://inaturalist-open-data.s3.amazonaws.com/photos/82351245/medium.jpg",
  "Heather": "https://inaturalist-open-data.s3.amazonaws.com/photos/121441132/medium.jpeg",
  "Common Box": "https://inaturalist-open-data.s3.amazonaws.com/photos/48987498/medium.jpeg",
  "Cornflower": "https://static.inaturalist.org/photos/28956867/medium.jpg",
  "Escallonia": "https://inaturalist-open-data.s3.amazonaws.com/photos/113821012/medium.jpg",
  "Euphorbia Mellifera": "https://inaturalist-open-data.s3.amazonaws.com/photos/2879554/medium.jpg",
  "Rosemary": "https://static.inaturalist.org/photos/87326219/medium.jpg",
  "Butterfly Bush": "https://inaturalist-open-data.s3.amazonaws.com/photos/34193/medium.jpg",
  "Elephant Garlic": "https://inaturalist-open-data.s3.amazonaws.com/photos/63378263/medium.jpg",
  "Rhubarb": "https://inaturalist-open-data.s3.amazonaws.com/photos/54802051/medium.jpeg",
  "Phlomis": "https://inaturalist-open-data.s3.amazonaws.com/photos/596839/medium.jpg",
  "Oak Tree": "https://inaturalist-open-data.s3.amazonaws.com/photos/90880312/medium.jpg",
  "Fir Tree": "https://inaturalist-open-data.s3.amazonaws.com/photos/108627343/medium.jpeg",
  "Asparagus Fern": "https://inaturalist-open-data.s3.amazonaws.com/photos/203493658/medium.jpeg",
  "Elm Tree": "https://inaturalist-open-data.s3.amazonaws.com/photos/14642890/medium.jpg",
  "Lady's Mantles": "https://static.inaturalist.org/photos/200085309/medium.jpeg",
  "Bergenia": "https://inaturalist-open-data.s3.amazonaws.com/photos/103138/medium.jpg",
  "Aucuba Japonica": "https://inaturalist-open-data.s3.amazonaws.com/photos/14055046/medium.jpeg"
}